panasonic_concat/__init__.py
panasonic_concat-1.0.1.data/scripts/panasonic-concat
panasonic_concat-1.0.1.dist-info/LICENSE
panasonic_concat-1.0.1.dist-info/METADATA
panasonic_concat-1.0.1.dist-info/WHEEL
panasonic_concat-1.0.1.dist-info/top_level.txt
panasonic_concat-1.0.1.dist-info/RECORD
